{
    "products": [
            {
                "id": "1",
                "name": "Loro Piana",
                "description": "Loro Piana",
                "full_description": " Men's Polo Shirt Golf Shirt Casual Holiday Classic Short Sleeve Fashion Basic Plain Button Summer Regular Fit Navy Black White Yellow Red Blue Polo Shirt 2024. Shop for cheap Classic Polo online? Buy at lightinthebox.com on sale today!",
                "price": 1299.99,
                "image": "https://i.im.ge/2024/03/05/8ETRUh.8c8e64f0258f1a0d36ca04557dad17e8-removebg-preview.png",
                "additionalDetails":{
                    "reviews": 4
                }
            },
            {
                "id": "2",
                "name": "Die Köhler Combat Pant",
                "description": "Cargo Pant",
               "full_description": "Die Köhler Combat Pant aus 50% Baumwolle und 50% Polyester Ripstop ist eine perfekte Kombination von Funktion, Verarbeitung und Material mit folgenden Details: 2 Einschubtaschen mit klettbarer Taschenklappe, die auch zum schnellen Zugriff in die Tasche eingeschoben werden kann, 2 große Gesäßtaschen, die leicht vergrößert werden und dadurch Magazine aufnehmen können, in den Gesäßtaschen befinden sich 2.",
                "price": 900.45,
                "image": "https://i.im.ge/2024/03/05/8EoGl9.431936df6fc0c68d7eba9b5c949e015a-removebg-preview.png",
                "additionalDetails":{
                    "reviews": 3
                }
            },
            {
                "id": "3",
                "name": "Men Zip Up Bomber Jacket",
                "description": "Slim fit striped silk and linen-Blended Polo shirt",
                "full_description": "Polyester Imported Zipper closure Hand Wash Only Lightweight and high-quality fabric,thicker than windbreaker material,comfortable and durable. Full zip-front closure.Long sleeve ,rib(collar,cuff and hem),functional pocket and inside pocket.",
                "price": 350.00,
                "image": "https://i.im.ge/2024/03/05/8Eoppz.ae3dfff4ec501e6ca9b778dfdad8fe58-removebg-preview.png",
                "additionalDetails":{
                    "reviews": 3
                }
            },
            {
                "id": "4",
                "name": "Classic Plain Short Sleeve",
                "description": "Holiday Summer Classic Short Sleeve",
                "full_description": " Men's Polo Shirt Golf Shirt Casual Holiday Classic Short Sleeve Fashion Basic Plain Button Summer Regular Fit Navy Black White Yellow Red Blue Polo Shirt 2024. Shop for cheap Classic Polo online? Buy at lightinthebox.com on sale today!",
                "price": 1020.33,
                "image": "https://i.im.ge/2024/03/05/8ETYFK.Men-Hollow-Out-Button-Up-Shirt-removebg-preview.png",
                "additionalDetails":{
                    "reviews": 5
                }
            },
            {
                "id": "5",
                "name": "Tara Upper Boots",
                "description": "Tara LeatherLining Upper Boots",
               "full_description": "Tara Boots Upper Material: Genuine LeatherLining Material: Short PlushShaft Material: Split LeatherInsole Material: Short PlushOutsole Material: RubberHeel height: About 5 cmShaft Hight: About 13 cmBoot Opening: About 24.5 cm We pay your attention to the fact that different computer screens can display different colors even though this is one and the same color. Therefore the color of the received good can be a little bit different than the good on the photo",
                "price": 1299.99,
                "image": "https://i.im.ge/2024/03/05/8ETvWP.10b70d0fa7366f3c9c09695c92e969c5-removebg-preview.png",
                "additionalDetails":{
                    "reviews": 3
                }
            },
            {
                "id": "6",
                "name": "Sporty Sneakers",
                "description": "Women Lace-Up Front Skate Shoes, Sporty Outdoor Sneakers",
               "full_description": "Category:Slip-Ons,Flats; Upper Materials:Tissage Volant; Season:Fall,Summer,Spring; Heel Type:Flat Heel; Gender:Women's; Activity:Walking; Toe Shape:Round Toe; Style:Minimalism,Casual; Heel Height(inch):<1; Outsole Materials:Rubber; Occasion:Outdoor,Daily; Closure Type:Loafer; Pattern:Solid Color; Listing Date:06/01/2023; Production mode:External procurement; 2024 Trends:Comfort Shoes; Foot Length:; Foot Width:; SizeChart1_ID:2:18404",
                "price": 1299.00,
                "image": "https://i.im.ge/2024/03/05/8El0tD.d3e1b28831f2eab7ebd04da4f9a7f4dd-removebg-preview.png",
                "additionalDetails":{
                    "reviews": 3
                }
            },
            {
                "id": "7",
                "name": "Casual women shoe",
                "description": "Red causual flat women shoe",
                "full_description": "Category:Slip-Ons,Flats; Upper Materials:Tissage Volant; Season:Fall,Summer,Spring; Heel Type:Flat Heel; Gender:Women's; Activity:Walking; Toe Shape:Round Toe; Style:Minimalism,Casual; Heel Height(inch):<1; Outsole Materials:Rubber; Occasion:Outdoor,Daily; Closure Type:Loafer; Pattern:Solid Color; Listing Date:06/01/2023; Production mode:External procurement; 2024 Trends:Comfort Shoes; Foot Length:; Foot Width:; SizeChart1_ID:2:18404",
                "price": 2000.00,
                "image": "https://i.im.ge/2024/03/05/8ETZ4Y.9a1e765132ffd2937a78c1535a21fa0f-removebg-preview.png",
                "additionalDetails":{
                    "reviews": 3
                }
            },
            {
                "id": "9",
                "name": " Air-jet  sweatpant",
                "description": "Original cool sweatpants",
               "full_description": "The original model of our stylish high quality pants will help to create your unique style. These are cool sweatpants with a large cargo pocket. We have fabrics of different colors, one of them you will definitely like. These high-quality original design joggers pants are great for both sports and outing",
                "price": 440.99,
                "image": "https://i.im.ge/2024/03/05/8Eoe0X.6a4b072d49c2322e7103ca119d8556ef-removebg-preview.png",
                "additionalDetails":{
                    "reviews": 3
                }
            },
            {
                "id": "8",
                "name": "Kicks Crew",
                "description": "Newest Classics sneakers.",
               "full_description": "KicksCrew provides everyone globally with a trusted source and the widest selection of sneakers and streetwear needs. From Newest Drops, Classics, Rare collectibles to Sports Needs. ",
                "price": 1000,
                "image": "https://i.im.ge/2024/03/05/8EQ7Cz.f799469c1e7c0f6770a5667753bc0179-removebg-preview.png",
                "additionalDetails":{
                    "reviews": 3
                }
            }
        ]
}